EASGen/EASGen.py
EASGen/__init__.py
EASGen_Remastered-0.1.14.1.dist-info/LICENSE
EASGen_Remastered-0.1.14.1.dist-info/METADATA
EASGen_Remastered-0.1.14.1.dist-info/WHEEL
EASGen_Remastered-0.1.14.1.dist-info/top_level.txt
EASGen_Remastered-0.1.14.1.dist-info/RECORD
