Metadata-Version: 2.1
Name: EASGen-Remastered
Version: 0.1.14.1
Summary: A Python library to generate EAS SAME Audio using Raw Data - Remastered
Home-page: https://github.com/Newton-Communications/EG
Author: secludedhusky
Author-email: secludedhusky@chesbaycommunications.com
License: ODbL-1.0
Keywords: audio sound eas alerting emergency-alert-system
Classifier: Development Status :: 5 - Production/Stable
Classifier: License :: Other/Proprietary License
Classifier: Programming Language :: Python
Classifier: Programming Language :: Python :: 3.6
Classifier: Programming Language :: Python :: 3.7
Classifier: Programming Language :: Python :: 3.8
Classifier: Programming Language :: Python :: 3.9
Classifier: Programming Language :: Python :: 3.10
Classifier: Programming Language :: Python :: 3.11
Classifier: Intended Audience :: Developers
Classifier: Operating System :: OS Independent
Classifier: Topic :: Multimedia :: Sound/Audio
Classifier: Topic :: Software Development :: Libraries
Classifier: Topic :: Utilities
License-File: LICENSE
Requires-Dist: EASGen
